{"type": "Feature", "id": 12510915, "geometry": {"type": "Point", "coordinates": [94.055603, 23.186899]}, "properties": {"woe:id": 12510915, "woe:parent_id": 1017441, "woe:name": "Kalemyo Airport", "woe:placetype": 14, "woe:placetype_name": "Airport", "woe:lang": "ENG", "iso:country": "MM", "meta:provider": ["geoplanet:7.3.1", "geoplanet:7.3.2", "geoplanet:7.4.0", "geoplanet:7.4.1", "geoplanet:7.5.1", "geoplanet:7.5.2", "geoplanet:7.6.0", "geoplanet:7.8.1", "geoplanet:7.9.0", "geoplanet:7.10.0", "geoplanet:8.0.0", "woeplanet:8.0.0"], "meta:indexed": "2020-08-20T20:49:06.898747", "woe:alias_ENG_V": ["KMV Airport", "KMV"], "meta:updated": "2020-10-14T11:15:13.857595", "woe:hierarchy": {"continent": 24865671, "country": 23424763, "town": 0, "planet": 1, "county": 0, "suburb": 0, "state": 2344819, "region": 0, "localadmin": 0}, "woe:timezone_id": 28350850, "woe:hash": "wh4gum11qrkb", "woe:centroid": [94.055603, 23.186899], "geom:latitude": 23.186899, "geom:longitude": 94.055603, "geom:hash": "wh4gum11qrkb", "woe:latitude": 23.186899, "geom:centroid": [94.055603, 23.186899], "woe:longitude": 94.055603, "woe:repo": "woeplanet-airport-mm", "geom:area": 0.0, "woe:scale": 19}}