{"type": "Feature", "id": 12510920, "geometry": {"type": "Point", "coordinates": [97.755798, 22.9767]}, "properties": {"woe:id": 12510920, "woe:parent_id": 1017541, "woe:name": "Lashio Airport", "woe:placetype": 14, "woe:placetype_name": "Airport", "woe:lang": "ENG", "iso:country": "MM", "meta:provider": ["geoplanet:7.3.1", "geoplanet:7.3.2", "geoplanet:7.4.0", "geoplanet:7.4.1", "geoplanet:7.5.1", "geoplanet:7.5.2", "geoplanet:7.6.0", "geoplanet:7.8.1", "geoplanet:7.9.0", "geoplanet:7.10.0", "geoplanet:8.0.0", "woeplanet:8.0.0"], "meta:indexed": "2020-08-20T20:49:06.903173", "woe:alias_ENG_V": ["LSH Airport", "LSH"], "meta:updated": "2020-10-14T11:15:13.863560", "woe:hierarchy": {"continent": 24865671, "country": 23424763, "town": 0, "planet": 1, "county": 0, "suburb": 0, "state": 2344820, "region": 0, "localadmin": 0}, "woe:timezone_id": 28350850, "woe:hash": "whjd8qz8gpq4", "woe:centroid": [97.755798, 22.9767], "geom:latitude": 22.9767, "geom:longitude": 97.755798, "geom:hash": "whjd8qz8gpq4", "woe:latitude": 22.9767, "geom:centroid": [97.755798, 22.9767], "woe:longitude": 97.755798, "woe:repo": "woeplanet-airport-mm", "geom:area": 0.0, "woe:scale": 19}}